grsq/__init__.py
grsq/accel.py
grsq/compton.py
grsq/damping.py
grsq/debye.py
grsq/grsq.py
grsq/histogramming.py
grsq/py.typed
grsq/data/HaiduCoefficients.txt
grsq-1.3.1.dist-info/licenses/LICENSE
grsq-1.3.1.dist-info/METADATA
grsq-1.3.1.dist-info/WHEEL
grsq-1.3.1.dist-info/top_level.txt
grsq-1.3.1.dist-info/RECORD
