Metadata-Version: 2.4
Name: grsq
Version: 1.3.1
Summary: Structure factor and X-ray scattering from radial distribution functions
Home-page: https://gitlab.com/asod/grsq
Author: Asmus Ougaard Dohn
Author-email: Asmus Ougaard Dohn <asmus.od@gmail.com>
License: MIT License
Project-URL: Homepage, https://gitlab.com/asod/grsq
Project-URL: Bug Tracker, https://gitlab.com/asod/grsq/issues
Project-URL: documentation, https://grsq.readthedocs.io/
Classifier: Programming Language :: Python :: 3
Classifier: License :: OSI Approved :: MIT License
Classifier: Operating System :: OS Independent
Requires-Python: >=3.7
License-File: LICENSE
Requires-Dist: numpy>=1.20.3
Requires-Dist: numba>=0.56.4
Requires-Dist: periodictable>=1.5.3
Requires-Dist: scipy>=1.6.2
Requires-Dist: MDAnalysis>=1.0.0
Requires-Dist: ase
Dynamic: license-file
